security_scanner.py
ai_code_scanner-1.0.0.dist-info/METADATA
ai_code_scanner-1.0.0.dist-info/WHEEL
ai_code_scanner-1.0.0.dist-info/entry_points.txt
ai_code_scanner-1.0.0.dist-info/top_level.txt
ai_code_scanner-1.0.0.dist-info/RECORD
