Metadata-Version: 2.1
Name: ai-code-scanner
Version: 1.0.0
Summary: A powerful Python tool that scans your codebase for security vulnerabilities using Claude AI
Home-page: https://github.com/yourusername/AI-CodeScanner
Author: Your Name
Author-email: your.email@example.com
License: UNKNOWN
Project-URL: Bug Reports, https://github.com/yourusername/AI-CodeScanner/issues
Project-URL: Source, https://github.com/yourusername/AI-CodeScanner
Project-URL: Documentation, https://github.com/yourusername/AI-CodeScanner#readme
Keywords: security,code,scanner,vulnerability,claude,ai,static-analysis
Platform: UNKNOWN
Classifier: Development Status :: 4 - Beta
Classifier: Intended Audience :: Developers
Classifier: License :: OSI Approved :: MIT License
Classifier: Operating System :: OS Independent
Classifier: Programming Language :: Python :: 3
Classifier: Programming Language :: Python :: 3.7
Classifier: Programming Language :: Python :: 3.8
Classifier: Programming Language :: Python :: 3.9
Classifier: Programming Language :: Python :: 3.10
Classifier: Programming Language :: Python :: 3.11
Classifier: Programming Language :: Python :: 3.12
Classifier: Topic :: Security
Classifier: Topic :: Software Development :: Quality Assurance
Classifier: Topic :: Software Development :: Testing
Requires-Python: >=3.7
Requires-Dist: anthropic (>=0.18.0)
Requires-Dist: pathlib2 (>=2.3.7) ; python_version < "3.4"
